unpredictablefate-3.0.1.dist-info/METADATA
unpredictablefate-3.0.1.dist-info/WHEEL
unpredictablefate-3.0.1.dist-info/licenses/LICENSE
unpredictablefate/__init__.py
unpredictablefate-3.0.1.dist-info/RECORD
