Metadata-Version: 2.1
Name: unpredictableFate
Version: 3.0.1
Summary: Official unF rule book.
Author-Email: 简律纯 <i@jyunko.cn>
License: MIT
Requires-Python: >=3.8
Requires-Dist: mkdocs>=1.5.3
Requires-Dist: mkdocs-material[imaging]>=9.4.4
Requires-Dist: mkdocs-blog-plugin>=0.25
Requires-Dist: mkdocs-git-revision-date-localized-plugin>=1.2.0
Requires-Dist: mkdocs-git-authors-plugin>=0.7.2
Requires-Dist: mkdocs-material-extensions>=1.2
Requires-Dist: neoteroi-mkdocs>=1.0.4
Requires-Dist: pillow~=9.4
Requires-Dist: cairosvg>=2.7.1
Requires-Dist: mkdocs-git-committers-plugin-2>=1.2.0
Requires-Dist: lxml>=4.9.3
Requires-Dist: mkdocs-minify-plugin>=0.7.1
Requires-Dist: mkdocs-rss-plugin>=1.8.0
Requires-Dist: mkdocs-redirects>=1.2.1
Requires-Dist: mike>=1.1.2
Requires-Dist: mkdocstrings>=0.23.0
Requires-Dist: distribute>=0.7.3
Requires-Dist: reportlab[pycairo]>=4.0.5
Requires-Dist: pydantic>=2.4.2
Requires-Dist: loguru>=0.7.2
